MANIFEST.in
readme.md
setup.py
smtpdev/__init__.py
smtpdev/cli.py
smtpdev/config.py
smtpdev/message_observer.py
smtpdev/smtp_handlers.py
smtpdev.egg-info/PKG-INFO
smtpdev.egg-info/SOURCES.txt
smtpdev.egg-info/dependency_links.txt
smtpdev.egg-info/entry_points.txt
smtpdev.egg-info/not-zip-safe
smtpdev.egg-info/requires.txt
smtpdev.egg-info/top_level.txt
smtpdev/__pycache__/__init__.cpython-37.pyc
smtpdev/__pycache__/__init__.cpython-38.pyc
smtpdev/__pycache__/cli.cpython-37.pyc
smtpdev/__pycache__/cli.cpython-38.pyc
smtpdev/__pycache__/config.cpython-37.pyc
smtpdev/__pycache__/config.cpython-38.pyc
smtpdev/__pycache__/message_observer.cpython-37.pyc
smtpdev/__pycache__/message_observer.cpython-38.pyc
smtpdev/__pycache__/smtp_handlers.cpython-37.pyc
smtpdev/__pycache__/smtp_handlers.cpython-38.pyc
smtpdev/__pycache__/utils.cpython-37.pyc
smtpdev/static/moment/moment-with-locales.min.js
smtpdev/static/vue/vue.min.js
smtpdev/static/vue-material/vue-material.min.css
smtpdev/static/vue-material/vue-material.min.js
smtpdev/static/vue-material/theme/black-green-dark.css
smtpdev/static/vue-material/theme/black-green-light.css
smtpdev/static/vue-material/theme/default-dark.css
smtpdev/static/vue-material/theme/default.css
smtpdev/templates/index.html
smtpdev/web_server/__init__.py
smtpdev/web_server/message.py
smtpdev/web_server/message_util.py
smtpdev/web_server/schemas.py
smtpdev/web_server/web_server.py
smtpdev/web_server/__pycache__/__init__.cpython-37.pyc
smtpdev/web_server/__pycache__/__init__.cpython-38.pyc
smtpdev/web_server/__pycache__/message.cpython-37.pyc
smtpdev/web_server/__pycache__/message.cpython-38.pyc
smtpdev/web_server/__pycache__/message_util.cpython-37.pyc
smtpdev/web_server/__pycache__/message_util.cpython-38.pyc
smtpdev/web_server/__pycache__/schemas.cpython-37.pyc
smtpdev/web_server/__pycache__/schemas.cpython-38.pyc
smtpdev/web_server/__pycache__/web_server.cpython-37.pyc
smtpdev/web_server/__pycache__/web_server.cpython-38.pyc