Metadata-Version: 1.1
Name: smtpdev
Version: 0.2.8
Summary: Asynchronous SMTP server for local development and email testing
Home-page: https://github.com/asyncee/smtpdev
Author: asyncee
Author-email: UNKNOWN
License: MIT
Download-URL: https://pypi.python.org/pypi/smtpdev/
Keywords: smtp developer server
Platform: UNKNOWN
Classifier: Development Status :: 5 - Production/Stable
Classifier: Intended Audience :: Developers
Classifier: License :: OSI Approved :: MIT License
Classifier: Programming Language :: Python
Classifier: Programming Language :: Python :: 3
Classifier: Programming Language :: Python :: 3.7
